pytest_falcon/__init__.py
pytest_falcon/plugin.py
pytest_falcon-0.4.2.dist-info/DESCRIPTION.rst
pytest_falcon-0.4.2.dist-info/METADATA
pytest_falcon-0.4.2.dist-info/RECORD
pytest_falcon-0.4.2.dist-info/WHEEL
pytest_falcon-0.4.2.dist-info/entry_points.txt
pytest_falcon-0.4.2.dist-info/metadata.json
pytest_falcon-0.4.2.dist-info/top_level.txt
