Metadata-Version: 1.1
Name: pytest-falcon
Version: 0.4.2
Summary: Pytest helpers for Falcon.
Home-page: https://github.com/yohanboniface/pytest-falcon
Author: Yohan Boniface
Author-email: yohan.boniface@data.gouv.fr
License: WTFPL
Keywords: pytest falcon testing unittests
Platform: UNKNOWN
Classifier: Development Status :: 4 - Beta
Classifier: Intended Audience :: Developers
Classifier: Topic :: Scientific/Engineering :: GIS
Classifier: Programming Language :: Python :: 2
Classifier: Programming Language :: Python :: 2.7
Classifier: Programming Language :: Python :: 3
Classifier: Programming Language :: Python :: 3.4
Classifier: Programming Language :: Python :: 3.5
